pyinseq/VERSION
pyinseq/__init__.py
pyinseq/analyze.py
pyinseq/config.py
pyinseq/demultiplex.py
pyinseq/gbk_convert.py
pyinseq/logger.py
pyinseq/map_reads.py
pyinseq/parsers.py
pyinseq/pipeline.py
pyinseq/process_mapping.py
pyinseq/settings.py
pyinseq/utils.py
pyinseq/envs/bowtie.yaml
pyinseq/tests/__init__.py
pyinseq/tests/test_functions.py
pyinseq/tests/test_script.py
pyinseq/tests/test_utils.py
pyinseq/tests/data/additional/sample01_01.txt
pyinseq/tests/data/additional/sample01_02.txt
pyinseq/tests/data/input/ES114v2.gb
pyinseq/tests/data/input/demultiplex-config.yml
pyinseq/tests/data/input/example01.fastq
pyinseq/tests/data/input/example01.txt
pyinseq/tests/data/input/example02.txt
pyinseq/tests/data/input/example03.fastq
pyinseq/tests/data/input/example03.txt
pyinseq/tests/data/input/genomeprep-config.yml
pyinseq/tests/data/input/test-pyinseq-config.yml
pyinseq/tests/data/output_demultiplex/E001_01_trimmed.fastq
pyinseq/tests/data/output_demultiplex/E001_02_trimmed.fastq
pyinseq/tests/data/output_demultiplex/log.txt
pyinseq/tests/data/output_demultiplex/samples.txt
pyinseq/tests/data/output_demultiplex/samples_info.yml
pyinseq/tests/data/output_demultiplex/summary_log.txt
pyinseq/tests/data/output_demultiplex/raw_data/E001_01.fastq
pyinseq/tests/data/output_demultiplex/raw_data/E001_02.fastq
pyinseq/tests/data/output_demultiplex/raw_data/_other.fastq
pyinseq/tests/data/output_demultiplex_notrim/log.txt
pyinseq/tests/data/output_demultiplex_notrim/samples.txt
pyinseq/tests/data/output_demultiplex_notrim/samples_info.yml
pyinseq/tests/data/output_demultiplex_notrim/summary_log.txt
pyinseq/tests/data/output_demultiplex_notrim/raw_data/E001_01.fastq
pyinseq/tests/data/output_demultiplex_notrim/raw_data/E001_02.fastq
pyinseq/tests/data/output_demultiplex_notrim/raw_data/_other.fastq
pyinseq/tests/data/output_genomeprep/log.txt
pyinseq/tests/data/output_genomeprep/genome_lookup/genome.1.ebwt
pyinseq/tests/data/output_genomeprep/genome_lookup/genome.2.ebwt
pyinseq-0.3.2.dist-info/LICENSE.md
pyinseq-0.3.2.dist-info/METADATA
pyinseq-0.3.2.dist-info/WHEEL
pyinseq-0.3.2.dist-info/top_level.txt
pyinseq-0.3.2.dist-info/RECORD
