Metadata-Version: 2.1
Name: pyinseq
Version: 0.3.2
Summary: Analysis of transposon insertion sequencing (INSeq) data in Python
Home-page: https://github.com/mjmlab/pyinseq
Author: Mark J. Mandel,Emanuel Burgos,Camille Scott,Loren Velasquez,Benjamin K. Johnson
Author-email: mandel01@gmail.com
License: BSD
Project-URL: Documentation, https://github.com/mjmlab/pyinseq/blob/master/README.md
Platform: MacOS
Platform: Linux/Unix
Classifier: Development Status :: 4 - Beta
Classifier: Intended Audience :: Science/Research
Classifier: License :: OSI Approved :: BSD License
Classifier: Operating System :: MacOS :: MacOS X
Classifier: Operating System :: POSIX
Classifier: Programming Language :: Python :: 3.7
Classifier: Programming Language :: Python :: 3.8
Classifier: Topic :: Scientific/Engineering :: Bio-Informatics
Requires-Python: !=3.9.*,>=3.7.*
License-File: LICENSE.md
Requires-Dist: black (>=18.9b0)
Requires-Dist: matplotlib (>=1.5.0)
Requires-Dist: seaborn (>=0.6.0)
Requires-Dist: numpy (>=1.10.0)
Requires-Dist: pandas (>=0.18.1)
Requires-Dist: pre-commit (>=1.12.0)
Requires-Dist: pytest (>=2.8.1)
Requires-Dist: pytest-cov (>=2.4.0)
Requires-Dist: codecov (>=2.0.5)
Requires-Dist: PyYAML (>=3.11)
Requires-Dist: screed (>=0.9)
Requires-Dist: snakemake (>=5.31.1)
Requires-Dist: tqdm (>=4.61.2)
